coronaweeklyJP.py
coronaweeklyJP-0.0.1.dist-info/LICENSE
coronaweeklyJP-0.0.1.dist-info/METADATA
coronaweeklyJP-0.0.1.dist-info/WHEEL
coronaweeklyJP-0.0.1.dist-info/entry_points.txt
coronaweeklyJP-0.0.1.dist-info/top_level.txt
coronaweeklyJP-0.0.1.dist-info/RECORD
